pyoverchain/__init__.py
pyoverchain/cmd/__init__.py
pyoverchain/cmd/run.py
pyoverchain/core/__init__.py
pyoverchain/core/axtchain.py
pyoverchain/core/blat.py
pyoverchain/core/chainMergeSort.py
pyoverchain/core/chainNet.py
pyoverchain/core/chr_separation.py
pyoverchain/core/faSplit.py
pyoverchain/core/liftUp.py
pyoverchain/core/netChainSubset.py
pyoverchain/core/pipeline_multiple.py
pyoverchain/core/pipeline_single.py
pyoverchain/core/version.py
pyoverchain-1.0.1.dist-info/LICENSE
pyoverchain-1.0.1.dist-info/METADATA
pyoverchain-1.0.1.dist-info/WHEEL
pyoverchain-1.0.1.dist-info/entry_points.txt
pyoverchain-1.0.1.dist-info/top_level.txt
pyoverchain-1.0.1.dist-info/RECORD
